ShapeCal.py
ShapeCal-0.0.2.dist-info/LICENSE
ShapeCal-0.0.2.dist-info/METADATA
ShapeCal-0.0.2.dist-info/WHEEL
ShapeCal-0.0.2.dist-info/entry_points.txt
ShapeCal-0.0.2.dist-info/top_level.txt
ShapeCal-0.0.2.dist-info/RECORD
